{
    "coord":{
        "lon":-0.1257,
        "lat":51.5085,
    },
    "weather":[
        {
            "id":802,
            "main":"Clouds",
            "description":"scattered clouds",
            "icon":"03n",
        }
    ],
    "base":"stations",
    "main":{
        "temp":282.47,
        "feels_like":280.79,
        "temp_min":280.64,
        "temp_max":283.35,
        "pressure":994,
        "humidity":80,
    },
    "visibility":10000,
    "wind":{
        "speed":3.09,
        "deg":300,
    },
    "clouds":{
        "all":40,
    },
    "dt":1707672453,
    "sys":{
        "type":2,
        "id":2075535,
        "country":"GB",
        "sunrise":1707636197,
        "sunset":1707671181,
    },
    "timezone":0,
    "id":2643743,
    "name":"London",
    "cod":200,
}
